folge_cli/__init__.py
folge_cli/cmd.py
folge_cli/documentation.py
folge_cli-0.1.0.dist-info/METADATA
folge_cli-0.1.0.dist-info/WHEEL
folge_cli-0.1.0.dist-info/entry_points.txt
folge_cli-0.1.0.dist-info/top_level.txt
folge_cli-0.1.0.dist-info/RECORD
