Metadata-Version: 2.1
Name: folge-cli
Version: 0.1.0
Summary: Client for the folge project
Home-page: https://github.com/labd/folge-cli
Author: Lab Digital
Author-email: opensource@labdigital.nl
License: MIT
Platform: UNKNOWN
Classifier: Development Status :: 5 - Production/Stable
Classifier: Environment :: Web Environment
Classifier: License :: OSI Approved :: MIT License
Classifier: Programming Language :: Python
Classifier: Programming Language :: Python :: 3
Classifier: Programming Language :: Python :: 3.6
Classifier: Programming Language :: Python :: 3.7
Classifier: Programming Language :: Python :: 3.8
Requires-Dist: requests (>=2.18.4)
Requires-Dist: click
Requires-Dist: click-default-group
Provides-Extra: docs
Requires-Dist: sphinx (>=1.4.0) ; extra == 'docs'
Provides-Extra: test
Requires-Dist: coverage[toml] (==5.0.3) ; extra == 'test'
Requires-Dist: requests-mock (==1.3.0) ; extra == 'test'
Requires-Dist: pytest-cov (>=2.2.0) ; extra == 'test'
Requires-Dist: pytest (>=2.8.3) ; extra == 'test'
Requires-Dist: pytest-click ; extra == 'test'
Requires-Dist: isort[pyproject] (==4.3.21) ; extra == 'test'
Requires-Dist: flake8 (==3.0.3) ; extra == 'test'
Requires-Dist: flake8-blind-except (==0.1.1) ; extra == 'test'
Requires-Dist: flake8-debugger (==1.4.0) ; extra == 'test'
Requires-Dist: flake8-imports ; extra == 'test'
